TGAMpy/TGAMpy.py
TGAMpy-0.0.1.dist-info/METADATA
TGAMpy-0.0.1.dist-info/WHEEL
TGAMpy-0.0.1.dist-info/top_level.txt
TGAMpy-0.0.1.dist-info/RECORD
